MANIFEST.in
README.md
requirements.txt
setup.cfg
setup.py
versioneer.py
botcity/plugins/files/__init__.py
botcity/plugins/files/_version.py
botcity/plugins/files/plugin.py
botcity/plugins/files/watchdog_utils.py
botcity_files_plugin.egg-info/PKG-INFO
botcity_files_plugin.egg-info/SOURCES.txt
botcity_files_plugin.egg-info/dependency_links.txt
botcity_files_plugin.egg-info/requires.txt
botcity_files_plugin.egg-info/top_level.txt