Metadata-Version: 2.1
Name: botcity-files-plugin
Version: 0.1.3
Home-page: https://bitbucket.org/botcitydev/bot-files-plugin-python.git
Requires-Python: >=3.7
